{"nodes": [{"id": "d_cropnow_cropdesk_frontend_nest_src_contexts_authcontext_tsx", "label": "AuthContext.tsx", "file_type": "code", "source_file": "D:\\cropnow\\cropdesk_Frontend_Nest\\src\\contexts\\AuthContext.tsx", "source_location": "L1"}, {"id": "authcontext_authprovider", "label": "AuthProvider()", "file_type": "code", "source_file": "D:\\cropnow\\cropdesk_Frontend_Nest\\src\\contexts\\AuthContext.tsx", "source_location": "L23"}, {"id": "authcontext_useauth", "label": "useAuth()", "file_type": "code", "source_file": "D:\\cropnow\\cropdesk_Frontend_Nest\\src\\contexts\\AuthContext.tsx", "source_location": "L103"}], "edges": [{"source": "d_cropnow_cropdesk_frontend_nest_src_contexts_authcontext_tsx", "target": "react", "relation": "imports_from", "confidence": "EXTRACTED", "source_file": "D:\\cropnow\\cropdesk_Frontend_Nest\\src\\contexts\\AuthContext.tsx", "source_location": "L1", "weight": 1.0}, {"source": "d_cropnow_cropdesk_frontend_nest_src_contexts_authcontext_tsx", "target": "react", "relation": "imports_from", "confidence": "EXTRACTED", "source_file": "D:\\cropnow\\cropdesk_Frontend_Nest\\src\\contexts\\AuthContext.tsx", "source_location": "L2", "weight": 1.0}, {"source": "d_cropnow_cropdesk_frontend_nest_src_contexts_authcontext_tsx", "target": "d_cropnow_cropdesk_frontend_nest_src_api_auth_api", "relation": "imports_from", "confidence": "EXTRACTED", "source_file": "D:\\cropnow\\cropdesk_Frontend_Nest\\src\\contexts\\AuthContext.tsx", "source_location": "L3", "weight": 1.0}, {"source": "d_cropnow_cropdesk_frontend_nest_src_contexts_authcontext_tsx", "target": "d_cropnow_cropdesk_frontend_nest_src_types_auth_types", "relation": "imports_from", "confidence": "EXTRACTED", "source_file": "D:\\cropnow\\cropdesk_Frontend_Nest\\src\\contexts\\AuthContext.tsx", "source_location": "L4", "weight": 1.0}, {"source": "d_cropnow_cropdesk_frontend_nest_src_contexts_authcontext_tsx", "target": "authcontext_authprovider", "relation": "contains", "confidence": "EXTRACTED", "source_file": "D:\\cropnow\\cropdesk_Frontend_Nest\\src\\contexts\\AuthContext.tsx", "source_location": "L23", "weight": 1.0}, {"source": "d_cropnow_cropdesk_frontend_nest_src_contexts_authcontext_tsx", "target": "authcontext_useauth", "relation": "contains", "confidence": "EXTRACTED", "source_file": "D:\\cropnow\\cropdesk_Frontend_Nest\\src\\contexts\\AuthContext.tsx", "source_location": "L103", "weight": 1.0}], "raw_calls": [{"caller_nid": "authcontext_authprovider", "callee": "useState", "source_file": "D:\\cropnow\\cropdesk_Frontend_Nest\\src\\contexts\\AuthContext.tsx", "source_location": "L24"}, {"caller_nid": "authcontext_authprovider", "callee": "useState", "source_file": "D:\\cropnow\\cropdesk_Frontend_Nest\\src\\contexts\\AuthContext.tsx", "source_location": "L25"}, {"caller_nid": "authcontext_authprovider", "callee": "useEffect", "source_file": "D:\\cropnow\\cropdesk_Frontend_Nest\\src\\contexts\\AuthContext.tsx", "source_location": "L28"}, {"caller_nid": "authcontext_authprovider", "callee": "useCallback", "source_file": "D:\\cropnow\\cropdesk_Frontend_Nest\\src\\contexts\\AuthContext.tsx", "source_location": "L49"}, {"caller_nid": "authcontext_authprovider", "callee": "useCallback", "source_file": "D:\\cropnow\\cropdesk_Frontend_Nest\\src\\contexts\\AuthContext.tsx", "source_location": "L75"}, {"caller_nid": "authcontext_authprovider", "callee": "useCallback", "source_file": "D:\\cropnow\\cropdesk_Frontend_Nest\\src\\contexts\\AuthContext.tsx", "source_location": "L87"}, {"caller_nid": "authcontext_useauth", "callee": "useContext", "source_file": "D:\\cropnow\\cropdesk_Frontend_Nest\\src\\contexts\\AuthContext.tsx", "source_location": "L104"}]}