{"nodes": [{"id": "d_cropnow_cropdesk_frontend_nest_src_pages_errors_unauthorizedpage_tsx", "label": "UnauthorizedPage.tsx", "file_type": "code", "source_file": "D:\\cropnow\\cropdesk_Frontend_Nest\\src\\pages\\errors\\UnauthorizedPage.tsx", "source_location": "L1"}, {"id": "unauthorizedpage_unauthorizedpage", "label": "UnauthorizedPage()", "file_type": "code", "source_file": "D:\\cropnow\\cropdesk_Frontend_Nest\\src\\pages\\errors\\UnauthorizedPage.tsx", "source_location": "L7"}], "edges": [{"source": "d_cropnow_cropdesk_frontend_nest_src_pages_errors_unauthorizedpage_tsx", "target": "react", "relation": "imports_from", "confidence": "EXTRACTED", "source_file": "D:\\cropnow\\cropdesk_Frontend_Nest\\src\\pages\\errors\\UnauthorizedPage.tsx", "source_location": "L5", "weight": 1.0}, {"source": "d_cropnow_cropdesk_frontend_nest_src_pages_errors_unauthorizedpage_tsx", "target": "unauthorizedpage_unauthorizedpage", "relation": "contains", "confidence": "EXTRACTED", "source_file": "D:\\cropnow\\cropdesk_Frontend_Nest\\src\\pages\\errors\\UnauthorizedPage.tsx", "source_location": "L7", "weight": 1.0}], "raw_calls": []}